pic_search/__init__.py
pic_search/cli.py
pic_search/ocr.py
pic_search_ocr-1.0.1.dist-info/METADATA
pic_search_ocr-1.0.1.dist-info/WHEEL
pic_search_ocr-1.0.1.dist-info/entry_points.txt
pic_search_ocr-1.0.1.dist-info/licenses/LICENSE
pic_search_ocr-1.0.1.dist-info/RECORD
