Metadata-Version: 2.4
Name: pic-search-ocr
Version: 1.0.1
Summary: Search the text of images in your folder with Tesseract OCR.
Project-URL: Repository, https://github.com/ryan-w-s/pic-search
Project-URL: Homepage, https://github.com/ryan-w-s/pic-search
Author: Ryan Stolliker
License: MIT
License-File: LICENSE
Requires-Python: >=3.11
Requires-Dist: pytesseract>=0.3.13
